{
  "1": {
    "name": "Spirit Blossom Ahri",
    "new" : "true",
    "1": {
      "name": "Orb of Deception",
      "cost": 2,
      "item1": "NAME",
      "item1Level": 0,
      "new" : "true"
    },
    "2": {
      "name": "Spirit Rush",
      "cost": 3,
      "item1": "NAME",
      "item1Level": 0,
      "new" : "true"
    },
    "3": {
      "name": "Essence Thief",
      "cost": 2,
      "item1": "NAME",
      "item1Level": 0,
      "new" : "true"
    },
    "4": {
      "name": "Serene Spirit",
      "cost": 3,
      "item1": "NAME",
      "item1Level": 0,
      "new" : "true"
    },
    "5": {
      "name": "Final Blessing",
      "cost": 5,
      "item1": "NAME",
      "item1Level": 0,
      "new" : "true"
    },
    "6": {
      "name": "Sparring Student",
      "cost": 1,
      "item1": "NAME",
      "item1Level": 0
    },
    "7": {
      "name": "Prancing Sea Spirits",
      "cost": 2,
      "item1": "NAME",
      "item1Level": 0
    },
    "8": {
      "name": "Petals of Fate",
      "cost": 1,
      "item1": "NAME",
      "item1Level": 0,
      "new" : "true"
    },
    "E1": {
      "name": "Fox-Fire",
      "item1": "NAME",
      "item1Level": 0,
      "new" : "true"
    }
  },
  "2": {
    "name": "Spirit Blossom Evelynn",
    "new" : "true",
    "1": {
      "name": "Mark of the Isles",
      "cost": 1,
      "item1": "NAME",
      "item1Level": 0,
      "item2": "NAME",
      "item2Level": 0
    },
    "2": {
      "name": "Stirred Spirits",
      "cost": 2,
      "item1": "NAME",
      "item1Level": 0,
      "item2": "NAME",
      "item2Level": 0,
      "new" : "true"
    },
    "3": {
      "name": "Fated Suplicant",
      "cost": 2,
      "item1": "NAME",
      "item1Level": 0,
      "item2": "NAME",
      "item2Level": 0,
      "new" : "true"
    },
    "4": {
      "name": "Spirit's Embrace",
      "cost": 3,
      "item1": "NAME",
      "item1Level": 0,
      "item2": "NAME",
      "item2Level": 0,
      "new" : "true"
    },
    "5": {
      "name": "Withering Wail",
      "cost": 4,
      "item1": "NAME",
      "item1Level": 0,
      "item2": "NAME",
      "item2Level": 0
    },
    "6": {
      "name": "Occult Oportunist",
      "cost": 3,
      "item1": "NAME",
      "item1Level": 0,
      "item2": "NAME",
      "item2Level": 0,
      "new" : "true"
    },
    "7": {
      "name": "Bewitch",
      "cost": 5,
      "item1": "NAME",
      "item1Level": 0,
      "item2": "NAME",
      "item2Level": 0,
      "new" : "true"
    },
    "8": {
      "name": "Shadow Swindler",
      "cost": 1,
      "item1": "NAME",
      "item1Level": 0,
      "item2": "NAME",
      "item2Level": 0,
      "new" : "true"
    },
    "E1": {
      "name": "Beckoning Gaze",
      "related": "",
      "item1": "NAME",
      "item1Level": 0,
      "item2": "NAME",
      "item2Level": 0,
      "new" : "true"
    }
  }
}
